finna_client.py
finna_client-0.2.1.dist-info/LICENSE.txt
finna_client-0.2.1.dist-info/METADATA
finna_client-0.2.1.dist-info/WHEEL
finna_client-0.2.1.dist-info/top_level.txt
finna_client-0.2.1.dist-info/RECORD
