Metadata-Version: 2.1
Name: finna-client
Version: 0.2.1
Summary: Python client library for accessing Finna REST API
Home-page: https://github.com/NatLibFi/Finna-client
Author: Osma Suominen
Author-email: osma.suominen@helsinki.fi
License: UNKNOWN
Platform: UNKNOWN
Classifier: Programming Language :: Python :: 3
Classifier: License :: OSI Approved :: Apache Software License
Classifier: Operating System :: OS Independent
Requires-Dist: requests
Provides-Extra: dev
Requires-Dist: bumpversion ; extra == 'dev'
